gbiz_torch/__init__.py
gbiz_torch/layer/__init__.py
gbiz_torch/layer/activation.py
gbiz_torch/layer/attention.py
gbiz_torch/layer/core.py
gbiz_torch/layer/interaction.py
gbiz_torch/layer/multimodality.py
gbiz_torch/layer/search.py
gbiz_torch/layer/sequence.py
gbiz_torch/layer/spatial.py
gbiz_torch/loss/__init__.py
gbiz_torch/loss/common_improved_loss.py
gbiz_torch/loss/cox_regression_loss.py
gbiz_torch/loss/self_supervised_loss.py
gbiz_torch/metrics/__init__.py
gbiz_torch/metrics/classification.py
gbiz_torch/metrics/manifold.py
gbiz_torch/metrics/regression.py
gbiz_torch/model/__init__.py
gbiz_torch/model/bert4rec.py
gbiz_torch/model/can.py
gbiz_torch/model/contextnet.py
gbiz_torch/model/cross_sharing_mtl.py
gbiz_torch/model/cross_stitch.py
gbiz_torch/model/dcap.py
gbiz_torch/model/dcn.py
gbiz_torch/model/deepfm.py
gbiz_torch/model/din.py
gbiz_torch/model/dnn.py
gbiz_torch/model/edcn.py
gbiz_torch/model/esmm.py
gbiz_torch/model/fbas.py
gbiz_torch/model/fibinet.py
gbiz_torch/model/flen.py
gbiz_torch/model/general_mmoe.py
gbiz_torch/model/general_multihead_attn.py
gbiz_torch/model/gru4rec.py
gbiz_torch/model/hard_sharing_mtl.py
gbiz_torch/model/interHAt.py
gbiz_torch/model/masknet.py
gbiz_torch/model/nfm.py
gbiz_torch/model/ple.py
gbiz_torch/model/tower.py
gbiz_torch/model/wnd.py
gbiz_torch-0.0.6.5.dist-info/LICENSE
gbiz_torch-0.0.6.5.dist-info/METADATA
gbiz_torch-0.0.6.5.dist-info/WHEEL
gbiz_torch-0.0.6.5.dist-info/top_level.txt
gbiz_torch-0.0.6.5.dist-info/RECORD
