Metadata-Version: 2.1
Name: gbiz_torch
Version: 0.0.6.5
Summary: general deep algorithm for business, marketing and advertisement
Home-page: https://github.com/whw199833/gbiz_torch
Author: Haowen Wang
Author-email: haowenw98@gmail.com
License: MIT
Classifier: Development Status :: 3 - Alpha
Classifier: Intended Audience :: Developers
Classifier: License :: OSI Approved :: MIT License
Classifier: Programming Language :: Python
Classifier: Programming Language :: Python :: 3.6
Classifier: Programming Language :: Python :: 3.7
Classifier: Programming Language :: Python :: 3.8
Classifier: Programming Language :: Python :: 3.9
Classifier: Programming Language :: Python :: 3.10
License-File: LICENSE
Requires-Dist: torch >=1.12.0
Requires-Dist: torch-geometric
Requires-Dist: scikit-learn >=1.2.2
Requires-Dist: pyg-lib
Requires-Dist: torch-scatter
Requires-Dist: torch-sparse
Requires-Dist: torch-cluster
Requires-Dist: torch-spline-conv
